traceforce/__init__.py
traceforce/module.py
traceforce-0.1.0.dist-info/licenses/LICENSE
traceforce-0.1.0.dist-info/METADATA
traceforce-0.1.0.dist-info/WHEEL
traceforce-0.1.0.dist-info/top_level.txt
traceforce-0.1.0.dist-info/RECORD
